Metadata-Version: 2.1
Name: biomed-multi-alignment
Version: 0.2.1
Summary: MAMMAL (Molecular Aligned Multi-Modal Architecture and Language), a flexible, multi-domain architecture with an adaptable task prompt syntax.
Author: IBM Research
Author-email: Moshe Raboh <moshiko.raboh@ibm.com>
License: Apache License
Project-URL: repository, https://github.com/BiomedSciAI/biomed-multi-alignment
Requires-Python: <3.13,>=3.10
License-File: LICENSE.txt
Requires-Dist: fuse-med-ml ==0.4.0
Requires-Dist: tensorflow >=2.17
Requires-Dist: peft
Requires-Dist: tabulate
Requires-Dist: clearml
Requires-Dist: hydra-core
Requires-Dist: pytest
Provides-Extra: examples
Requires-Dist: PyTDC ; extra == 'examples'
